setup.cfg
setup.py
melipayamak/__init__.py
melipayamak/branch.py
melipayamak/contacts.py
melipayamak/melipayamak.py
melipayamak/ticket.py
melipayamak/users.py
melipayamak/sms/__init__.py
melipayamak/sms/rest.py
melipayamak/sms/soap.py
mymelipayamak.egg-info/PKG-INFO
mymelipayamak.egg-info/SOURCES.txt
mymelipayamak.egg-info/dependency_links.txt
mymelipayamak.egg-info/requires.txt
mymelipayamak.egg-info/top_level.txt