Metadata-Version: 1.1
Name: mymelipayamak
Version: 1.0.0
Summary: MeliPayamak Python library
Home-page: https://github.com/Melipayamak/melipayamak-python
Author: Melipayamak Team
Author-email: UNKNOWN
License: UNKNOWN
Keywords: melipayamak,sms
Platform: UNKNOWN
Classifier: Programming Language :: Python
Classifier: Operating System :: OS Independent
Classifier: Intended Audience :: Developers
Classifier: Development Status :: 5 - Production/Stable
Classifier: Topic :: Software Development :: Libraries :: Python Modules
Classifier: Topic :: Communications :: Telephony
